LICENSE
README.md
setup.cfg
setup.py
src/APIAlchemy.egg-info/PKG-INFO
src/APIAlchemy.egg-info/SOURCES.txt
src/APIAlchemy.egg-info/dependency_links.txt
src/APIAlchemy.egg-info/not-zip-safe
src/APIAlchemy.egg-info/requires.txt
src/APIAlchemy.egg-info/top_level.txt
src/apialchemy/__init__.py
src/apialchemy/service/__init__.py
src/apialchemy/vendors/__init__.py
src/apialchemy/vendors/appdynamics/__init__.py
src/apialchemy/vendors/extrahop/__init__.py
src/apialchemy/vendors/extrahop/client.py
src/apialchemy/vendors/github/__init__.py
src/apialchemy/vendors/graphite/__init__.py
src/apialchemy/vendors/graphite/client.py
src/apialchemy/vendors/newrelic/__init__.py
src/apialchemy/vendors/newrelic/client.py
src/apialchemy/vendors/prometheus/__init__.py
src/apialchemy/vendors/pushgateway/__init__.py
src/apialchemy/vendors/pushgateway/client.py
src/apialchemy/vendors/solarwinds/__init__.py
src/apialchemy/vendors/splunk/__init__.py
src/apialchemy/vendors/wavefront/__init__.py
src/apialchemy/vendors/wavefront/client.py