Metadata-Version: 2.1
Name: APIAlchemy
Version: 1.3.0
Summary: API toolkit for Python, modeled after SQLAlchemy
Home-page: https://github.com/homedepot/apialchemy
Author: Mike Phillipson
Author-email: MICHAEL_PHILLIPSON1@homedepot.com
License: MIT
Platform: UNKNOWN
License-File: LICENSE
